openpnm/__init__.py
openpnm/_skgraph/__init__.py
openpnm/_skgraph/generators/__init__.py
openpnm/_skgraph/generators/_bcc.py
openpnm/_skgraph/generators/_cubic.py
openpnm/_skgraph/generators/_delaunay.py
openpnm/_skgraph/generators/_fcc.py
openpnm/_skgraph/generators/_gabriel.py
openpnm/_skgraph/generators/_template.py
openpnm/_skgraph/generators/_voronoi.py
openpnm/_skgraph/generators/_voronoi_delaunay_dual.py
openpnm/_skgraph/generators/network
openpnm/_skgraph/generators/tools/__init__.py
openpnm/_skgraph/generators/tools/_funcs.py
openpnm/_skgraph/io/__init__.py
openpnm/_skgraph/io/_funcs.py
openpnm/_skgraph/operations/__init__.py
openpnm/_skgraph/operations/_binary.py
openpnm/_skgraph/operations/_funcs.py
openpnm/_skgraph/operations/_unary.py
openpnm/_skgraph/queries/QuickUnion.py
openpnm/_skgraph/queries/__init__.py
openpnm/_skgraph/queries/_funcs.py
openpnm/_skgraph/queries/_qupc.py
openpnm/_skgraph/simulations/__init__.py
openpnm/_skgraph/simulations/_funcs.py
openpnm/_skgraph/simulations/_percolation.py
openpnm/_skgraph/tools/GraphBundle.py
openpnm/_skgraph/tools/__init__.py
openpnm/_skgraph/tools/_coords_transforms.py
openpnm/_skgraph/tools/_funcs.py
openpnm/_skgraph/visualization/__init__.py
openpnm/_skgraph/visualization/_funcs.py
openpnm/algorithms/__init__.py
openpnm/algorithms/_advection_diffusion.py
openpnm/algorithms/_algorithm.py
openpnm/algorithms/_drainage.py
openpnm/algorithms/_fickian_diffusion.py
openpnm/algorithms/_fourier_conduction.py
openpnm/algorithms/_invasion_percolation.py
openpnm/algorithms/_ohmic_conduction.py
openpnm/algorithms/_reactive_transport.py
openpnm/algorithms/_solution.py
openpnm/algorithms/_stokes_flow.py
openpnm/algorithms/_transient_advection_diffusion.py
openpnm/algorithms/_transient_fickian_diffusion.py
openpnm/algorithms/_transient_fourier_conduction.py
openpnm/algorithms/_transient_reactive_transport.py
openpnm/algorithms/_transport.py
openpnm/beta/__init__.py
openpnm/beta/_funcs.py
openpnm/contrib/__init__.py
openpnm-3.6.0.dist-info/METADATA
openpnm-3.6.0.dist-info/WHEEL
openpnm-3.6.0.dist-info/licenses/LICENSE
openpnm-3.6.0.dist-info/RECORD
