Metadata-Version: 2.4
Name: openpnm
Version: 3.6.0
Summary: A framework for conducting pore network modeling simulations of multiphase transport in porous materials
Project-URL: Homepage, https://openpnm.org
Project-URL: Repository, https://github.com/PMEAL/OpenPNM
Project-URL: Bug Tracker, https://github.com/PMEAL/OpenPNM/issues
Project-URL: Documentation, https://openpnm.org
Author-email: OpenPNM Team <jgostick@gmail.com>
Maintainer-email: Jeff Gostick <jgostick@gmail.com>, Amin Sadeghi <amin.sadeghi@live.com>
License-Expression: MIT
License-File: LICENSE
Classifier: Development Status :: 5 - Production/Stable
Classifier: Operating System :: OS Independent
Classifier: Programming Language :: Python
Classifier: Programming Language :: Python :: 3
Classifier: Topic :: Scientific/Engineering
Classifier: Topic :: Scientific/Engineering :: Physics
Requires-Python: <3.14,>=3.11
Requires-Dist: docrep>=0.3.2
Requires-Dist: h5py>=3.14.0
Requires-Dist: jsonschema>=4.25.1
Requires-Dist: llvmlite>=0.44
Requires-Dist: matplotlib-inline>=0.1.7
Requires-Dist: matplotlib>=3.10.6
Requires-Dist: networkx>=3.5
Requires-Dist: numba>=0.61
Requires-Dist: numpy<2.2
Requires-Dist: pandas>=2.3.2
Requires-Dist: pyamg>=5.3.0
Requires-Dist: pypardiso; platform_system != 'Darwin' and (platform_machine == 'x86_64' or platform_machine == 'AMD64')
Requires-Dist: rich>=14.1.0
Requires-Dist: scikit-image>=0.25.0
Requires-Dist: scipy>=1.16.2
Requires-Dist: sympy>=1.14.0
Requires-Dist: thermo>=0.4.2
Requires-Dist: tqdm>=4.67.1
Requires-Dist: transforms3d>=0.4.2
Provides-Extra: extras
Requires-Dist: ngsolve; extra == 'extras'
Requires-Dist: porespy; extra == 'extras'
